README.md
setup.py
cvtorch/__init__.py
cvtorch/cvBox.py
cvtorch/cvEnhance.py
cvtorch/cvFunctional.py
cvtorch/cvTransforms.py
cvtorch.egg-info/PKG-INFO
cvtorch.egg-info/SOURCES.txt
cvtorch.egg-info/dependency_links.txt
cvtorch.egg-info/requires.txt
cvtorch.egg-info/top_level.txt