Metadata-Version: 1.0
Name: cvtorch
Version: 0.0.9
Summary: vision tools based on opencv
Home-page: UNKNOWN
Author: iHateTa11B0y
Author-email: 1187203155@qq.com
License: UNKNOWN
Platform: UNKNOWN
